<BackupInst xmlns="http://www.microsoft.com/GroupPolicy/GPOOperations/Manifest"><GPOGuid><![CDATA[{AB1B30A4-0088-41B7-AFEF-5D598F9E2950}]]></GPOGuid><GPODomain><![CDATA[homelab.local]]></GPODomain><GPODomainGuid><![CDATA[{4ec7c1a8-4063-46d5-b9dc-9e6f6235a446}]]></GPODomainGuid><GPODomainController><![CDATA[DC1.homelab.local]]></GPODomainController><BackupTime><![CDATA[2026-05-31T20:16:55]]></BackupTime><ID><![CDATA[{FE949AF8-D144-4C81-9B4A-FE49D95A5828}]]></ID><Comment><![CDATA[]]></Comment><GPODisplayName><![CDATA[Service Account Policy]]></GPODisplayName></BackupInst>
